pygarch/__init__.py
pygarch/exceptions.py
pygarch/proc.py
pygarch/spec.py
pygarch/lib/fit.R
pygarch/lib/spec.R
pygarch-0.0.2.dist-info/LICENSE
pygarch-0.0.2.dist-info/METADATA
pygarch-0.0.2.dist-info/WHEEL
pygarch-0.0.2.dist-info/top_level.txt
pygarch-0.0.2.dist-info/RECORD
