Metadata-Version: 2.1
Name: pygarch
Version: 0.0.2
Summary: UNKNOWN
Home-page: https://gitlab.corp.vesparum.com/oliver.chambers/pygarch
Author: Oliver Chambers
Author-email: UNKNOWN
License: UNKNOWN
Platform: UNKNOWN
Classifier: Programming Language :: Python :: 3.6
Classifier: License :: OSI Approved :: MIT License
Classifier: Operating System :: OS Independent
Classifier: Topic :: Utilities
Requires-Dist: pandas
Requires-Dist: rpy2 (<3)
